scrutineer/__init__.py
scrutineer/scrutineer.py
hive_scrutineer-1.3.18.dist-info/WHEEL
hive_scrutineer-1.3.18.dist-info/METADATA
hive_scrutineer-1.3.18.dist-info/licenses/LICENSE
hive_scrutineer-1.3.18.dist-info/RECORD
